monitoro_herd/__init__.py
monitoro_herd/main.py
monitoro_herd-0.1.5.dist-info/licenses/LICENSE
monitoro_herd-0.1.5.dist-info/METADATA
monitoro_herd-0.1.5.dist-info/WHEEL
monitoro_herd-0.1.5.dist-info/top_level.txt
monitoro_herd-0.1.5.dist-info/RECORD
