Metadata-Version: 2.4
Name: monitoro-herd
Version: 0.1.5
Summary: Python SDK for Monitoro Herd
Home-page: https://herd.garden
Author: Omar Kamali
Author-email: pypi@herd.garden
License: EULA
Keywords: browser,automation,web,scraping,browser-control,remote-browser,browser-extension,puppeteer,chrome,edge,brave,opera,arc,data-extraction,web-automation,mcp,model,context,protocol
Classifier: Development Status :: 3 - Alpha
Classifier: Intended Audience :: Developers
Classifier: Programming Language :: Python :: 3
Classifier: Programming Language :: Python :: 3.8
Classifier: Programming Language :: Python :: 3.9
Classifier: Programming Language :: Python :: 3.10
Classifier: Programming Language :: Python :: 3.11
Classifier: Programming Language :: Python :: 3.12
Classifier: Operating System :: OS Independent
Classifier: Topic :: Internet :: WWW/HTTP
Classifier: Topic :: Internet :: WWW/HTTP :: Browsers
Classifier: Topic :: Internet :: WWW/HTTP :: Dynamic Content
Classifier: Topic :: Internet :: WWW/HTTP :: Session
Classifier: Topic :: Software Development :: Libraries
Classifier: Topic :: Software Development :: Libraries :: Python Modules
Classifier: Topic :: Software Development :: Libraries :: Application Frameworks
License-File: LICENSE
Requires-Dist: aiohttp>=3.8.0
Requires-Dist: nats-py>=2.2.0
Requires-Dist: sseclient-py>=1.7.2
Requires-Dist: nkeys>=0.1.0
Requires-Dist: python-dateutil>=2.8.0
Provides-Extra: test
Requires-Dist: pytest>=7.4.0; extra == "test"
Requires-Dist: pytest-asyncio>=0.21.0; extra == "test"
Requires-Dist: python-dotenv>=1.0.0; extra == "test"
Dynamic: author
Dynamic: author-email
Dynamic: classifier
Dynamic: description
Dynamic: description-content-type
Dynamic: home-page
Dynamic: keywords
Dynamic: license
Dynamic: license-file
Dynamic: provides-extra
Dynamic: requires-dist
Dynamic: summary
